alfi/__init__.py
alfi/configuration.py
alfi/datasets/__init__.py
alfi/datasets/artificial.py
alfi/datasets/datasets.py
alfi/datasets/lfm_dataset.py
alfi/datasets/loaders.py
alfi/datasets/lotkavolterra.py
alfi/datasets/toy.py
alfi/datasets/toy_spatial.py
alfi/impl/__init__.py
alfi/impl/odes/__init__.py
alfi/impl/odes/lotka.py
alfi/impl/odes/transcriptional.py
alfi/impl/pdes/__init__.py
alfi/impl/pdes/reaction_diffusion.py
alfi/kernels/__init__.py
alfi/kernels/sim.py
alfi/mcmc/__init__.py
alfi/mcmc/parameter.py
alfi/mcmc/results.py
alfi/mcmc/gp/__init__.py
alfi/mcmc/gp/gp_kernels.py
alfi/mcmc/models/__init__.py
alfi/mcmc/models/model.py
alfi/mcmc/models/transcriptional.py
alfi/mcmc/samplers/__init__.py
alfi/mcmc/samplers/delay.py
alfi/mcmc/samplers/gibbs.py
alfi/mcmc/samplers/hmc.py
alfi/mcmc/samplers/latent.py
alfi/mcmc/samplers/mh.py
alfi/mcmc/samplers/mixed.py
alfi/mcmc/samplers/mixins.py
alfi/means/__init__.py
alfi/means/sim.py
alfi/mlls/__init__.py
alfi/mlls/masked_variational_elbo.py
alfi/models/__init__.py
alfi/models/approximate_gp.py
alfi/models/exact_lfm.py
alfi/models/lfm.py
alfi/models/mlp.py
alfi/models/neural_lfm.py
alfi/models/operator.py
alfi/models/ordinary_lfm.py
alfi/models/ordinary_lfm_no_precompute.py
alfi/models/partial_lfm.py
alfi/models/recurrent_operator.py
alfi/models/variational_lfm.py
alfi/nn/__init__.py
alfi/nn/conv_block.py
alfi/nn/conv_block_nn.py
alfi/nn/encoders.py
alfi/nn/lp_loss.py
alfi/nn/spectral_conv.py
alfi/plot/__init__.py
alfi/plot/base_plotter.py
alfi/plot/colours.py
alfi/plot/mcmc_plotters.py
alfi/plot/misc.py
alfi/plot/plotter1d.py
alfi/plot/plotter2d.py
alfi/trainers/__init__.py
alfi/trainers/base.py
alfi/trainers/exact.py
alfi/trainers/neural_lfm.py
alfi/trainers/operator.py
alfi/trainers/partial.py
alfi/trainers/preestimator.py
alfi/trainers/torte.py
alfi/trainers/variational.py
alfi/utilities/__init__.py
alfi/utilities/data.py
alfi/utilities/fenics.py
alfi/utilities/tf.py
alfi/utilities/torch.py
experiments/__init__.py
alfi-1.0.2.dist-info/LICENSE
alfi-1.0.2.dist-info/METADATA
alfi-1.0.2.dist-info/WHEEL
alfi-1.0.2.dist-info/top_level.txt
alfi-1.0.2.dist-info/RECORD
