Metadata-Version: 2.1
Name: alfi
Version: 1.0.2
Summary: An approximate latent force model library with variational inference for non-linear ODEs and PDEs.
Home-page: https://github.com/mossjacob/lafomo
Author: Jacob Moss
Author-email: cob.mossy@gmail.com
Classifier: Programming Language :: Python :: 3
Classifier: License :: OSI Approved :: MIT License
Classifier: Operating System :: OS Independent
Requires-Python: >=3.6
License-File: LICENSE
Requires-Dist: torch >=1.7.1
Requires-Dist: torchdiffeq >=0.2.0
Requires-Dist: pandas >=1.2.1
Requires-Dist: matplotlib
Requires-Dist: gpytorch >=1.3.1
